{
  "seo_keywords": [],
  "_id": "63b4821b2a77a80023e20dfa",
  "project_id": "63b47fbd017c8a001a3cdad7",
  "workspace_id": "63b4821a2a77a80023e20df9",
  "logo": "https://assets.tiledesk.com/images/23r3uj-chasqui_logo.png",
  "favicon": "https://assets.tiledesk.com/images/23r3uj-favicon-96x96.png",
  "header_color": "#71667c",
  "custom": true,
  "title": "Chasqui",
  "subtitle": "Comunidad de consumo solidario",
  "widget": "all_categories",
  "widget_id": "63b47fbd017c8a001a3cdad7",
  "index": true,
  "cover_image": null,
  "seo_title": "Chasqui",
  "seo_tagline": "Comunidad de consumo solidario",
  "seo_description": "Sistema de ayuda de proyecto Chasqui",
  "google_site_verification": null,
  "google_analytics": null,
  "lastUpdate": "2023-01-12T15:18:19.957Z",
  "guide": "",
  "site": "https://tiendaschasqui.ar",
  "first_menu_title": "Tiendas",
  "second_menu_title": "",
  "signup": "",
  "third_menu_title": "",
  "instagram_url": "https://www.instagram.com/proyectochasquiok/",
  "website": "https://tiendaschasqui.ar/",
  "widget_active": true
}
